{"nodes": [{"id": "c_arbeit_winharpoon_src_hotkeys_rs", "label": "hotkeys.rs", "file_type": "code", "source_file": "C:\\Arbeit\\winharpoon\\src\\hotkeys.rs", "source_location": "L1"}, {"id": "src_hotkeys_hotkeyaction", "label": "HotkeyAction", "file_type": "code", "source_file": "C:\\Arbeit\\winharpoon\\src\\hotkeys.rs", "source_location": "L24"}, {"id": "src_hotkeys_hotkeyregistrationresult", "label": "HotkeyRegistrationResult", "file_type": "code", "source_file": "C:\\Arbeit\\winharpoon\\src\\hotkeys.rs", "source_location": "L35"}, {"id": "src_hotkeys_hotkeymanager", "label": "HotkeyManager", "file_type": "code", "source_file": "C:\\Arbeit\\winharpoon\\src\\hotkeys.rs", "source_location": "L42"}, {"id": "src_hotkeys_hotkeymanager_register", "label": ".register()", "file_type": "code", "source_file": "C:\\Arbeit\\winharpoon\\src\\hotkeys.rs", "source_location": "L49"}, {"id": "src_hotkeys_hotkeymanager_reload", "label": ".reload()", "file_type": "code", "source_file": "C:\\Arbeit\\winharpoon\\src\\hotkeys.rs", "source_location": "L70"}, {"id": "src_hotkeys_hotkeymanager_conflict_count", "label": ".conflict_count()", "file_type": "code", "source_file": "C:\\Arbeit\\winharpoon\\src\\hotkeys.rs", "source_location": "L83"}, {"id": "src_hotkeys_hotkeymanager_apply_bindings", "label": ".apply_bindings()", "file_type": "code", "source_file": "C:\\Arbeit\\winharpoon\\src\\hotkeys.rs", "source_location": "L87"}, {"id": "src_hotkeys_hotkeymanager_unregister_all", "label": ".unregister_all()", "file_type": "code", "source_file": "C:\\Arbeit\\winharpoon\\src\\hotkeys.rs", "source_location": "L134"}, {"id": "src_hotkeys_hotkeymanager_report_conflicts", "label": ".report_conflicts()", "file_type": "code", "source_file": "C:\\Arbeit\\winharpoon\\src\\hotkeys.rs", "source_location": "L145"}, {"id": "src_hotkeys_hotkeymanager_run_message_loop", "label": ".run_message_loop()", "file_type": "code", "source_file": "C:\\Arbeit\\winharpoon\\src\\hotkeys.rs", "source_location": "L164"}, {"id": "src_hotkeys_post_reload", "label": "post_reload()", "file_type": "code", "source_file": "C:\\Arbeit\\winharpoon\\src\\hotkeys.rs", "source_location": "L195"}, {"id": "src_hotkeys_post_quit", "label": "post_quit()", "file_type": "code", "source_file": "C:\\Arbeit\\winharpoon\\src\\hotkeys.rs", "source_location": "L205"}, {"id": "src_hotkeys_hotkeymanager_drop", "label": ".drop()", "file_type": "code", "source_file": "C:\\Arbeit\\winharpoon\\src\\hotkeys.rs", "source_location": "L213"}, {"id": "src_hotkeys_report_config_errors", "label": "report_config_errors()", "file_type": "code", "source_file": "C:\\Arbeit\\winharpoon\\src\\hotkeys.rs", "source_location": "L219"}, {"id": "src_hotkeys_create_message_window", "label": "create_message_window()", "file_type": "code", "source_file": "C:\\Arbeit\\winharpoon\\src\\hotkeys.rs", "source_location": "L236"}, {"id": "src_hotkeys_window_proc", "label": "window_proc()", "file_type": "code", "source_file": "C:\\Arbeit\\winharpoon\\src\\hotkeys.rs", "source_location": "L265"}], "edges": [{"source": "c_arbeit_winharpoon_src_hotkeys_rs", "target": "hashmap", "relation": "imports_from", "confidence": "EXTRACTED", "source_file": "C:\\Arbeit\\winharpoon\\src\\hotkeys.rs", "source_location": "L1", "weight": 1.0, "context": "import"}, {"source": "c_arbeit_winharpoon_src_hotkeys_rs", "target": "atomic", "relation": "imports_from", "confidence": "EXTRACTED", "source_file": "C:\\Arbeit\\winharpoon\\src\\hotkeys.rs", "source_location": "L2", "weight": 1.0, "context": "import"}, {"source": "c_arbeit_winharpoon_src_hotkeys_rs", "target": "arc", "relation": "imports_from", "confidence": "EXTRACTED", "source_file": "C:\\Arbeit\\winharpoon\\src\\hotkeys.rs", "source_location": "L3", "weight": 1.0, "context": "import"}, {"source": "c_arbeit_winharpoon_src_hotkeys_rs", "target": "mutex", "relation": "imports_from", "confidence": "EXTRACTED", "source_file": "C:\\Arbeit\\winharpoon\\src\\hotkeys.rs", "source_location": "L5", "weight": 1.0, "context": "import"}, {"source": "c_arbeit_winharpoon_src_hotkeys_rs", "target": "foundation", "relation": "imports_from", "confidence": "EXTRACTED", "source_file": "C:\\Arbeit\\winharpoon\\src\\hotkeys.rs", "source_location": "L6", "weight": 1.0, "context": "import"}, {"source": "c_arbeit_winharpoon_src_hotkeys_rs", "target": "getmodulehandlew", "relation": "imports_from", "confidence": "EXTRACTED", "source_file": "C:\\Arbeit\\winharpoon\\src\\hotkeys.rs", "source_location": "L7", "weight": 1.0, "context": "import"}, {"source": "c_arbeit_winharpoon_src_hotkeys_rs", "target": "keyboardandmouse", "relation": "imports_from", "confidence": "EXTRACTED", "source_file": "C:\\Arbeit\\winharpoon\\src\\hotkeys.rs", "source_location": "L8", "weight": 1.0, "context": "import"}, {"source": "c_arbeit_winharpoon_src_hotkeys_rs", "target": "windowsandmessaging", "relation": "imports_from", "confidence": "EXTRACTED", "source_file": "C:\\Arbeit\\winharpoon\\src\\hotkeys.rs", "source_location": "L9", "weight": 1.0, "context": "import"}, {"source": "c_arbeit_winharpoon_src_hotkeys_rs", "target": "appstate", "relation": "imports_from", "confidence": "EXTRACTED", "source_file": "C:\\Arbeit\\winharpoon\\src\\hotkeys.rs", "source_location": "L14", "weight": 1.0, "context": "import"}, {"source": "c_arbeit_winharpoon_src_hotkeys_rs", "target": "config", "relation": "imports_from", "confidence": "EXTRACTED", "source_file": "C:\\Arbeit\\winharpoon\\src\\hotkeys.rs", "source_location": "L15", "weight": 1.0, "context": "import"}, {"source": "c_arbeit_winharpoon_src_hotkeys_rs", "target": "log", "relation": "imports_from", "confidence": "EXTRACTED", "source_file": "C:\\Arbeit\\winharpoon\\src\\hotkeys.rs", "source_location": "L16", "weight": 1.0, "context": "import"}, {"source": "c_arbeit_winharpoon_src_hotkeys_rs", "target": "src_hotkeys_hotkeyaction", "relation": "contains", "confidence": "EXTRACTED", "source_file": "C:\\Arbeit\\winharpoon\\src\\hotkeys.rs", "source_location": "L24", "weight": 1.0}, {"source": "c_arbeit_winharpoon_src_hotkeys_rs", "target": "src_hotkeys_hotkeyregistrationresult", "relation": "contains", "confidence": "EXTRACTED", "source_file": "C:\\Arbeit\\winharpoon\\src\\hotkeys.rs", "source_location": "L35", "weight": 1.0}, {"source": "c_arbeit_winharpoon_src_hotkeys_rs", "target": "src_hotkeys_hotkeymanager", "relation": "contains", "confidence": "EXTRACTED", "source_file": "C:\\Arbeit\\winharpoon\\src\\hotkeys.rs", "source_location": "L42", "weight": 1.0}, {"source": "src_hotkeys_hotkeymanager", "target": "src_hotkeys_hotkeymanager_register", "relation": "method", "confidence": "EXTRACTED", "source_file": "C:\\Arbeit\\winharpoon\\src\\hotkeys.rs", "source_location": "L49", "weight": 1.0}, {"source": "src_hotkeys_hotkeymanager", "target": "src_hotkeys_hotkeymanager_reload", "relation": "method", "confidence": "EXTRACTED", "source_file": "C:\\Arbeit\\winharpoon\\src\\hotkeys.rs", "source_location": "L70", "weight": 1.0}, {"source": "src_hotkeys_hotkeymanager", "target": "src_hotkeys_hotkeymanager_conflict_count", "relation": "method", "confidence": "EXTRACTED", "source_file": "C:\\Arbeit\\winharpoon\\src\\hotkeys.rs", "source_location": "L83", "weight": 1.0}, {"source": "src_hotkeys_hotkeymanager", "target": "src_hotkeys_hotkeymanager_apply_bindings", "relation": "method", "confidence": "EXTRACTED", "source_file": "C:\\Arbeit\\winharpoon\\src\\hotkeys.rs", "source_location": "L87", "weight": 1.0}, {"source": "src_hotkeys_hotkeymanager", "target": "src_hotkeys_hotkeymanager_unregister_all", "relation": "method", "confidence": "EXTRACTED", "source_file": "C:\\Arbeit\\winharpoon\\src\\hotkeys.rs", "source_location": "L134", "weight": 1.0}, {"source": "src_hotkeys_hotkeymanager", "target": "src_hotkeys_hotkeymanager_report_conflicts", "relation": "method", "confidence": "EXTRACTED", "source_file": "C:\\Arbeit\\winharpoon\\src\\hotkeys.rs", "source_location": "L145", "weight": 1.0}, {"source": "src_hotkeys_hotkeymanager", "target": "src_hotkeys_hotkeymanager_run_message_loop", "relation": "method", "confidence": "EXTRACTED", "source_file": "C:\\Arbeit\\winharpoon\\src\\hotkeys.rs", "source_location": "L164", "weight": 1.0}, {"source": "c_arbeit_winharpoon_src_hotkeys_rs", "target": "src_hotkeys_post_reload", "relation": "contains", "confidence": "EXTRACTED", "source_file": "C:\\Arbeit\\winharpoon\\src\\hotkeys.rs", "source_location": "L195", "weight": 1.0}, {"source": "c_arbeit_winharpoon_src_hotkeys_rs", "target": "src_hotkeys_post_quit", "relation": "contains", "confidence": "EXTRACTED", "source_file": "C:\\Arbeit\\winharpoon\\src\\hotkeys.rs", "source_location": "L205", "weight": 1.0}, {"source": "src_hotkeys_hotkeymanager", "target": "src_hotkeys_hotkeymanager_drop", "relation": "method", "confidence": "EXTRACTED", "source_file": "C:\\Arbeit\\winharpoon\\src\\hotkeys.rs", "source_location": "L213", "weight": 1.0}, {"source": "c_arbeit_winharpoon_src_hotkeys_rs", "target": "src_hotkeys_report_config_errors", "relation": "contains", "confidence": "EXTRACTED", "source_file": "C:\\Arbeit\\winharpoon\\src\\hotkeys.rs", "source_location": "L219", "weight": 1.0}, {"source": "c_arbeit_winharpoon_src_hotkeys_rs", "target": "src_hotkeys_create_message_window", "relation": "contains", "confidence": "EXTRACTED", "source_file": "C:\\Arbeit\\winharpoon\\src\\hotkeys.rs", "source_location": "L236", "weight": 1.0}, {"source": "c_arbeit_winharpoon_src_hotkeys_rs", "target": "src_hotkeys_window_proc", "relation": "contains", "confidence": "EXTRACTED", "source_file": "C:\\Arbeit\\winharpoon\\src\\hotkeys.rs", "source_location": "L265", "weight": 1.0}, {"source": "src_hotkeys_hotkeymanager_register", "target": "src_hotkeys_create_message_window", "relation": "calls", "context": "call", "confidence": "EXTRACTED", "source_file": "C:\\Arbeit\\winharpoon\\src\\hotkeys.rs", "source_location": "L51", "weight": 1.0}, {"source": "src_hotkeys_hotkeymanager_register", "target": "src_hotkeys_hotkeymanager_apply_bindings", "relation": "calls", "context": "call", "confidence": "EXTRACTED", "source_file": "C:\\Arbeit\\winharpoon\\src\\hotkeys.rs", "source_location": "L59", "weight": 1.0}, {"source": "src_hotkeys_hotkeymanager_register", "target": "src_hotkeys_hotkeymanager_conflict_count", "relation": "calls", "context": "call", "confidence": "EXTRACTED", "source_file": "C:\\Arbeit\\winharpoon\\src\\hotkeys.rs", "source_location": "L60", "weight": 1.0}, {"source": "src_hotkeys_hotkeymanager_register", "target": "src_hotkeys_hotkeymanager_report_conflicts", "relation": "calls", "context": "call", "confidence": "EXTRACTED", "source_file": "C:\\Arbeit\\winharpoon\\src\\hotkeys.rs", "source_location": "L66", "weight": 1.0}, {"source": "src_hotkeys_hotkeymanager_reload", "target": "src_hotkeys_hotkeymanager_unregister_all", "relation": "calls", "context": "call", "confidence": "EXTRACTED", "source_file": "C:\\Arbeit\\winharpoon\\src\\hotkeys.rs", "source_location": "L72", "weight": 1.0}, {"source": "src_hotkeys_hotkeymanager_reload", "target": "src_hotkeys_hotkeymanager_apply_bindings", "relation": "calls", "context": "call", "confidence": "EXTRACTED", "source_file": "C:\\Arbeit\\winharpoon\\src\\hotkeys.rs", "source_location": "L73", "weight": 1.0}, {"source": "src_hotkeys_hotkeymanager_reload", "target": "src_hotkeys_hotkeymanager_conflict_count", "relation": "calls", "context": "call", "confidence": "EXTRACTED", "source_file": "C:\\Arbeit\\winharpoon\\src\\hotkeys.rs", "source_location": "L74", "weight": 1.0}, {"source": "src_hotkeys_hotkeymanager_reload", "target": "src_hotkeys_hotkeymanager_report_conflicts", "relation": "calls", "context": "call", "confidence": "EXTRACTED", "source_file": "C:\\Arbeit\\winharpoon\\src\\hotkeys.rs", "source_location": "L80", "weight": 1.0}, {"source": "src_hotkeys_hotkeymanager_drop", "target": "src_hotkeys_hotkeymanager_unregister_all", "relation": "calls", "context": "call", "confidence": "EXTRACTED", "source_file": "C:\\Arbeit\\winharpoon\\src\\hotkeys.rs", "source_location": "L215", "weight": 1.0}], "raw_calls": [{"caller_nid": "src_hotkeys_hotkeymanager_register", "callee": "debug", "is_member_call": false, "source_file": "C:\\Arbeit\\winharpoon\\src\\hotkeys.rs", "source_location": "L50"}, {"caller_nid": "src_hotkeys_hotkeymanager_register", "callee": "store", "is_member_call": true, "source_file": "C:\\Arbeit\\winharpoon\\src\\hotkeys.rs", "source_location": "L52"}, {"caller_nid": "src_hotkeys_hotkeymanager_register", "callee": "debug", "is_member_call": false, "source_file": "C:\\Arbeit\\winharpoon\\src\\hotkeys.rs", "source_location": "L53"}, {"caller_nid": "src_hotkeys_hotkeymanager_register", "callee": "new", "is_member_call": false, "source_file": "C:\\Arbeit\\winharpoon\\src\\hotkeys.rs", "source_location": "L56"}, {"caller_nid": "src_hotkeys_hotkeymanager_register", "callee": "new", "is_member_call": false, "source_file": "C:\\Arbeit\\winharpoon\\src\\hotkeys.rs", "source_location": "L57"}, {"caller_nid": "src_hotkeys_hotkeymanager_register", "callee": "lock", "is_member_call": true, "source_file": "C:\\Arbeit\\winharpoon\\src\\hotkeys.rs", "source_location": "L62"}, {"caller_nid": "src_hotkeys_hotkeymanager_register", "callee": "clone", "is_member_call": true, "source_file": "C:\\Arbeit\\winharpoon\\src\\hotkeys.rs", "source_location": "L64"}, {"caller_nid": "src_hotkeys_hotkeymanager_reload", "callee": "debug", "is_member_call": false, "source_file": "C:\\Arbeit\\winharpoon\\src\\hotkeys.rs", "source_location": "L71"}, {"caller_nid": "src_hotkeys_hotkeymanager_reload", "callee": "lock", "is_member_call": true, "source_file": "C:\\Arbeit\\winharpoon\\src\\hotkeys.rs", "source_location": "L76"}, {"caller_nid": "src_hotkeys_hotkeymanager_reload", "callee": "clone", "is_member_call": true, "source_file": "C:\\Arbeit\\winharpoon\\src\\hotkeys.rs", "source_location": "L78"}, {"caller_nid": "src_hotkeys_hotkeymanager_conflict_count", "callee": "count", "is_member_call": true, "source_file": "C:\\Arbeit\\winharpoon\\src\\hotkeys.rs", "source_location": "L84"}, {"caller_nid": "src_hotkeys_hotkeymanager_conflict_count", "callee": "filter", "is_member_call": true, "source_file": "C:\\Arbeit\\winharpoon\\src\\hotkeys.rs", "source_location": "L84"}, {"caller_nid": "src_hotkeys_hotkeymanager_conflict_count", "callee": "iter", "is_member_call": true, "source_file": "C:\\Arbeit\\winharpoon\\src\\hotkeys.rs", "source_location": "L84"}, {"caller_nid": "src_hotkeys_hotkeymanager_apply_bindings", "callee": "clear", "is_member_call": true, "source_file": "C:\\Arbeit\\winharpoon\\src\\hotkeys.rs", "source_location": "L88"}, {"caller_nid": "src_hotkeys_hotkeymanager_apply_bindings", "callee": "clear", "is_member_call": true, "source_file": "C:\\Arbeit\\winharpoon\\src\\hotkeys.rs", "source_location": "L89"}, {"caller_nid": "src_hotkeys_hotkeymanager_apply_bindings", "callee": "debug", "is_member_call": false, "source_file": "C:\\Arbeit\\winharpoon\\src\\hotkeys.rs", "source_location": "L94"}, {"caller_nid": "src_hotkeys_hotkeymanager_apply_bindings", "callee": "is_ok", "is_member_call": true, "source_file": "C:\\Arbeit\\winharpoon\\src\\hotkeys.rs", "source_location": "L103"}, {"caller_nid": "src_hotkeys_hotkeymanager_apply_bindings", "callee": "RegisterHotKey", "is_member_call": false, "source_file": "C:\\Arbeit\\winharpoon\\src\\hotkeys.rs", "source_location": "L103"}, {"caller_nid": "src_hotkeys_hotkeymanager_apply_bindings", "callee": "HOT_KEY_MODIFIERS", "is_member_call": false, "source_file": "C:\\Arbeit\\winharpoon\\src\\hotkeys.rs", "source_location": "L106"}, {"caller_nid": "src_hotkeys_hotkeymanager_apply_bindings", "callee": "insert", "is_member_call": true, "source_file": "C:\\Arbeit\\winharpoon\\src\\hotkeys.rs", "source_location": "L112"}, {"caller_nid": "src_hotkeys_hotkeymanager_apply_bindings", "callee": "debug", "is_member_call": false, "source_file": "C:\\Arbeit\\winharpoon\\src\\hotkeys.rs", "source_location": "L113"}, {"caller_nid": "src_hotkeys_hotkeymanager_apply_bindings", "callee": "warn", "is_member_call": false, "source_file": "C:\\Arbeit\\winharpoon\\src\\hotkeys.rs", "source_location": "L119"}, {"caller_nid": "src_hotkeys_hotkeymanager_apply_bindings", "callee": "Some", "is_member_call": false, "source_file": "C:\\Arbeit\\winharpoon\\src\\hotkeys.rs", "source_location": "L123"}, {"caller_nid": "src_hotkeys_hotkeymanager_apply_bindings", "callee": "into", "is_member_call": true, "source_file": "C:\\Arbeit\\winharpoon\\src\\hotkeys.rs", "source_location": "L123"}, {"caller_nid": "src_hotkeys_hotkeymanager_apply_bindings", "callee": "push", "is_member_call": true, "source_file": "C:\\Arbeit\\winharpoon\\src\\hotkeys.rs", "source_location": "L125"}, {"caller_nid": "src_hotkeys_hotkeymanager_apply_bindings", "callee": "clone", "is_member_call": true, "source_file": "C:\\Arbeit\\winharpoon\\src\\hotkeys.rs", "source_location": "L126"}, {"caller_nid": "src_hotkeys_hotkeymanager_apply_bindings", "callee": "clone", "is_member_call": true, "source_file": "C:\\Arbeit\\winharpoon\\src\\hotkeys.rs", "source_location": "L127"}, {"caller_nid": "src_hotkeys_hotkeymanager_unregister_all", "callee": "collect", "is_member_call": true, "source_file": "C:\\Arbeit\\winharpoon\\src\\hotkeys.rs", "source_location": "L135"}, {"caller_nid": "src_hotkeys_hotkeymanager_unregister_all", "callee": "copied", "is_member_call": true, "source_file": "C:\\Arbeit\\winharpoon\\src\\hotkeys.rs", "source_location": "L135"}, {"caller_nid": "src_hotkeys_hotkeymanager_unregister_all", "callee": "keys", "is_member_call": true, "source_file": "C:\\Arbeit\\winharpoon\\src\\hotkeys.rs", "source_location": "L135"}, {"caller_nid": "src_hotkeys_hotkeymanager_unregister_all", "callee": "debug", "is_member_call": false, "source_file": "C:\\Arbeit\\winharpoon\\src\\hotkeys.rs", "source_location": "L136"}, {"caller_nid": "src_hotkeys_hotkeymanager_unregister_all", "callee": "UnregisterHotKey", "is_member_call": false, "source_file": "C:\\Arbeit\\winharpoon\\src\\hotkeys.rs", "source_location": "L139"}, {"caller_nid": "src_hotkeys_hotkeymanager_unregister_all", "callee": "clear", "is_member_call": true, "source_file": "C:\\Arbeit\\winharpoon\\src\\hotkeys.rs", "source_location": "L142"}, {"caller_nid": "src_hotkeys_hotkeymanager_report_conflicts", "callee": "warn", "is_member_call": false, "source_file": "C:\\Arbeit\\winharpoon\\src\\hotkeys.rs", "source_location": "L154"}, {"caller_nid": "src_hotkeys_hotkeymanager_report_conflicts", "callee": "debug", "is_member_call": false, "source_file": "C:\\Arbeit\\winharpoon\\src\\hotkeys.rs", "source_location": "L157"}, {"caller_nid": "src_hotkeys_hotkeymanager_run_message_loop", "callee": "debug", "is_member_call": false, "source_file": "C:\\Arbeit\\winharpoon\\src\\hotkeys.rs", "source_location": "L171"}, {"caller_nid": "src_hotkeys_hotkeymanager_run_message_loop", "callee": "zeroed", "is_member_call": false, "source_file": "C:\\Arbeit\\winharpoon\\src\\hotkeys.rs", "source_location": "L173"}, {"caller_nid": "src_hotkeys_hotkeymanager_run_message_loop", "callee": "as_bool", "is_member_call": true, "source_file": "C:\\Arbeit\\winharpoon\\src\\hotkeys.rs", "source_location": "L174"}, {"caller_nid": "src_hotkeys_hotkeymanager_run_message_loop", "callee": "GetMessageW", "is_member_call": false, "source_file": "C:\\Arbeit\\winharpoon\\src\\hotkeys.rs", "source_location": "L174"}, {"caller_nid": "src_hotkeys_hotkeymanager_run_message_loop", "callee": "copied", "is_member_call": true, "source_file": "C:\\Arbeit\\winharpoon\\src\\hotkeys.rs", "source_location": "L177"}, {"caller_nid": "src_hotkeys_hotkeymanager_run_message_loop", "callee": "get", "is_member_call": true, "source_file": "C:\\Arbeit\\winharpoon\\src\\hotkeys.rs", "source_location": "L177"}, {"caller_nid": "src_hotkeys_hotkeymanager_run_message_loop", "callee": "debug", "is_member_call": false, "source_file": "C:\\Arbeit\\winharpoon\\src\\hotkeys.rs", "source_location": "L178"}, {"caller_nid": "src_hotkeys_hotkeymanager_run_message_loop", "callee": "on_action", "is_member_call": false, "source_file": "C:\\Arbeit\\winharpoon\\src\\hotkeys.rs", "source_location": "L179"}, {"caller_nid": "src_hotkeys_hotkeymanager_run_message_loop", "callee": "warn", "is_member_call": false, "source_file": "C:\\Arbeit\\winharpoon\\src\\hotkeys.rs", "source_location": "L181"}, {"caller_nid": "src_hotkeys_hotkeymanager_run_message_loop", "callee": "debug", "is_member_call": false, "source_file": "C:\\Arbeit\\winharpoon\\src\\hotkeys.rs", "source_location": "L184"}, {"caller_nid": "src_hotkeys_hotkeymanager_run_message_loop", "callee": "on_reload", "is_member_call": false, "source_file": "C:\\Arbeit\\winharpoon\\src\\hotkeys.rs", "source_location": "L185"}, {"caller_nid": "src_hotkeys_hotkeymanager_run_message_loop", "callee": "TranslateMessage", "is_member_call": false, "source_file": "C:\\Arbeit\\winharpoon\\src\\hotkeys.rs", "source_location": "L187"}, {"caller_nid": "src_hotkeys_hotkeymanager_run_message_loop", "callee": "DispatchMessageW", "is_member_call": false, "source_file": "C:\\Arbeit\\winharpoon\\src\\hotkeys.rs", "source_location": "L188"}, {"caller_nid": "src_hotkeys_hotkeymanager_run_message_loop", "callee": "on_poll", "is_member_call": false, "source_file": "C:\\Arbeit\\winharpoon\\src\\hotkeys.rs", "source_location": "L189"}, {"caller_nid": "src_hotkeys_post_reload", "callee": "load", "is_member_call": true, "source_file": "C:\\Arbeit\\winharpoon\\src\\hotkeys.rs", "source_location": "L196"}, {"caller_nid": "src_hotkeys_post_reload", "callee": "debug", "is_member_call": false, "source_file": "C:\\Arbeit\\winharpoon\\src\\hotkeys.rs", "source_location": "L197"}, {"caller_nid": "src_hotkeys_post_reload", "callee": "PostMessageW", "is_member_call": false, "source_file": "C:\\Arbeit\\winharpoon\\src\\hotkeys.rs", "source_location": "L200"}, {"caller_nid": "src_hotkeys_post_reload", "callee": "HWND", "is_member_call": false, "source_file": "C:\\Arbeit\\winharpoon\\src\\hotkeys.rs", "source_location": "L200"}, {"caller_nid": "src_hotkeys_post_reload", "callee": "WPARAM", "is_member_call": false, "source_file": "C:\\Arbeit\\winharpoon\\src\\hotkeys.rs", "source_location": "L200"}, {"caller_nid": "src_hotkeys_post_reload", "callee": "LPARAM", "is_member_call": false, "source_file": "C:\\Arbeit\\winharpoon\\src\\hotkeys.rs", "source_location": "L200"}, {"caller_nid": "src_hotkeys_post_quit", "callee": "debug", "is_member_call": false, "source_file": "C:\\Arbeit\\winharpoon\\src\\hotkeys.rs", "source_location": "L206"}, {"caller_nid": "src_hotkeys_post_quit", "callee": "PostQuitMessage", "is_member_call": false, "source_file": "C:\\Arbeit\\winharpoon\\src\\hotkeys.rs", "source_location": "L208"}, {"caller_nid": "src_hotkeys_hotkeymanager_drop", "callee": "debug", "is_member_call": false, "source_file": "C:\\Arbeit\\winharpoon\\src\\hotkeys.rs", "source_location": "L214"}, {"caller_nid": "src_hotkeys_report_config_errors", "callee": "warn", "is_member_call": false, "source_file": "C:\\Arbeit\\winharpoon\\src\\hotkeys.rs", "source_location": "L224"}, {"caller_nid": "src_hotkeys_report_config_errors", "callee": "notify", "is_member_call": false, "source_file": "C:\\Arbeit\\winharpoon\\src\\hotkeys.rs", "source_location": "L225"}, {"caller_nid": "src_hotkeys_report_config_errors", "callee": "warn", "is_member_call": false, "source_file": "C:\\Arbeit\\winharpoon\\src\\hotkeys.rs", "source_location": "L229"}, {"caller_nid": "src_hotkeys_report_config_errors", "callee": "notify", "is_member_call": false, "source_file": "C:\\Arbeit\\winharpoon\\src\\hotkeys.rs", "source_location": "L230"}, {"caller_nid": "src_hotkeys_create_message_window", "callee": "wide", "is_member_call": false, "source_file": "C:\\Arbeit\\winharpoon\\src\\hotkeys.rs", "source_location": "L237"}, {"caller_nid": "src_hotkeys_create_message_window", "callee": "unwrap", "is_member_call": true, "source_file": "C:\\Arbeit\\winharpoon\\src\\hotkeys.rs", "source_location": "L238"}, {"caller_nid": "src_hotkeys_create_message_window", "callee": "GetModuleHandleW", "is_member_call": false, "source_file": "C:\\Arbeit\\winharpoon\\src\\hotkeys.rs", "source_location": "L238"}, {"caller_nid": "src_hotkeys_create_message_window", "callee": "Some", "is_member_call": false, "source_file": "C:\\Arbeit\\winharpoon\\src\\hotkeys.rs", "source_location": "L241"}, {"caller_nid": "src_hotkeys_create_message_window", "callee": "into", "is_member_call": true, "source_file": "C:\\Arbeit\\winharpoon\\src\\hotkeys.rs", "source_location": "L242"}, {"caller_nid": "src_hotkeys_create_message_window", "callee": "PCWSTR", "is_member_call": false, "source_file": "C:\\Arbeit\\winharpoon\\src\\hotkeys.rs", "source_location": "L243"}, {"caller_nid": "src_hotkeys_create_message_window", "callee": "as_ptr", "is_member_call": true, "source_file": "C:\\Arbeit\\winharpoon\\src\\hotkeys.rs", "source_location": "L243"}, {"caller_nid": "src_hotkeys_create_message_window", "callee": "default", "is_member_call": false, "source_file": "C:\\Arbeit\\winharpoon\\src\\hotkeys.rs", "source_location": "L244"}, {"caller_nid": "src_hotkeys_create_message_window", "callee": "RegisterClassW", "is_member_call": false, "source_file": "C:\\Arbeit\\winharpoon\\src\\hotkeys.rs", "source_location": "L246"}, {"caller_nid": "src_hotkeys_create_message_window", "callee": "expect", "is_member_call": true, "source_file": "C:\\Arbeit\\winharpoon\\src\\hotkeys.rs", "source_location": "L248"}, {"caller_nid": "src_hotkeys_create_message_window", "callee": "CreateWindowExW", "is_member_call": false, "source_file": "C:\\Arbeit\\winharpoon\\src\\hotkeys.rs", "source_location": "L248"}, {"caller_nid": "src_hotkeys_create_message_window", "callee": "default", "is_member_call": false, "source_file": "C:\\Arbeit\\winharpoon\\src\\hotkeys.rs", "source_location": "L249"}, {"caller_nid": "src_hotkeys_create_message_window", "callee": "PCWSTR", "is_member_call": false, "source_file": "C:\\Arbeit\\winharpoon\\src\\hotkeys.rs", "source_location": "L250"}, {"caller_nid": "src_hotkeys_create_message_window", "callee": "as_ptr", "is_member_call": true, "source_file": "C:\\Arbeit\\winharpoon\\src\\hotkeys.rs", "source_location": "L250"}, {"caller_nid": "src_hotkeys_create_message_window", "callee": "PCWSTR", "is_member_call": false, "source_file": "C:\\Arbeit\\winharpoon\\src\\hotkeys.rs", "source_location": "L251"}, {"caller_nid": "src_hotkeys_create_message_window", "callee": "as_ptr", "is_member_call": true, "source_file": "C:\\Arbeit\\winharpoon\\src\\hotkeys.rs", "source_location": "L251"}, {"caller_nid": "src_hotkeys_window_proc", "callee": "debug", "is_member_call": false, "source_file": "C:\\Arbeit\\winharpoon\\src\\hotkeys.rs", "source_location": "L272"}, {"caller_nid": "src_hotkeys_window_proc", "callee": "PostQuitMessage", "is_member_call": false, "source_file": "C:\\Arbeit\\winharpoon\\src\\hotkeys.rs", "source_location": "L273"}, {"caller_nid": "src_hotkeys_window_proc", "callee": "LRESULT", "is_member_call": false, "source_file": "C:\\Arbeit\\winharpoon\\src\\hotkeys.rs", "source_location": "L274"}, {"caller_nid": "src_hotkeys_window_proc", "callee": "DefWindowProcW", "is_member_call": false, "source_file": "C:\\Arbeit\\winharpoon\\src\\hotkeys.rs", "source_location": "L276"}]}